bodhisearch/__init__.py
bodhisearch/__main__.py
bodhisearch/hookspecs.py
bodhisearch/llm.py
bodhisearch/main.py
bodhisearch/openai/__init__.py
bodhisearch/openai/llm.py
bodhisearch/plugin.py
bodhisearch/prompt.py
bodhisearch-0.1.0.dist-info/METADATA
bodhisearch-0.1.0.dist-info/WHEEL
bodhisearch-0.1.0.dist-info/RECORD
