Metadata-Version: 2.1
Name: bodhisearch
Version: 0.1.0
Summary: intuitive and powerful library to work with LLMs
Author: Amir Nagri
Author-email: amir.nagri@proton.me
Requires-Python: >=3.8.1,<3.12
Classifier: Programming Language :: Python :: 3
Classifier: Programming Language :: Python :: 3.9
Classifier: Programming Language :: Python :: 3.10
Classifier: Programming Language :: Python :: 3.11
Requires-Dist: openai (>=0.27.8,<0.28.0)
Requires-Dist: pluggy (>=1.2.0,<2.0.0)
Requires-Dist: pytest-dotenv (>=0.5.2,<0.6.0)
Requires-Dist: python-dotenv (>=1.0.0,<2.0.0)
